waccy/__init__.py
waccy/cli.py
waccy/classification/__init__.py
waccy/classification/confidence.py
waccy/classification/engine.py
waccy/classification/patterns.py
waccy/core/__init__.py
waccy/core/models.py
waccy/core/ontology.py
waccy/core/validation.py
waccy/extraction/__init__.py
waccy/extraction/base.py
waccy/extraction/mapper.py
waccy/extraction/registry.py
waccy/modeling/__init__.py
waccy/modeling/builder.py
waccy/modeling/exporters.py
waccy/modeling/templates.py
waccy/utils/__init__.py
waccy/utils/dates.py
waccy/utils/formatting.py
waccy/utils/validation.py
waccy-0.0.2.dist-info/METADATA
waccy-0.0.2.dist-info/WHEEL
waccy-0.0.2.dist-info/entry_points.txt
waccy-0.0.2.dist-info/licenses/LICENSE
waccy-0.0.2.dist-info/RECORD
