Metadata-Version: 2.4
Name: waccy
Version: 0.0.2
Summary: Intelligent financial modeling platform for small businesses
Project-URL: Homepage, https://github.com/DecisionNerd/waccy
Project-URL: Repository, https://github.com/DecisionNerd/waccy
Project-URL: Issues, https://github.com/DecisionNerd/waccy/issues
Project-URL: Documentation, https://github.com/DecisionNerd/waccy#readme
Author: WACCY Contributors
License: MIT
License-File: LICENSE
Keywords: accounting,finance,financial-modeling,valuation
Classifier: Development Status :: 3 - Alpha
Classifier: Intended Audience :: Financial and Insurance Industry
Classifier: License :: OSI Approved :: MIT License
Classifier: Programming Language :: Python :: 3.13
Classifier: Topic :: Office/Business :: Financial
Requires-Python: >=3.13
Requires-Dist: numpy>=2.3.5
Requires-Dist: pandera>=0.27.0
Requires-Dist: polars>=1.36.1
Requires-Dist: pydantic>=2.12.5
Provides-Extra: edgar
Requires-Dist: waccy-edgar>=0.0.1; extra == 'edgar'
Provides-Extra: quickbooks
Requires-Dist: waccy-quickbooks>=0.0.1; extra == 'quickbooks'
